paginate_pandas/__init__.py
paginate_pandas/paginate.py
paginate_pandas-1.0.0.dist-info/LICENSE
paginate_pandas-1.0.0.dist-info/METADATA
paginate_pandas-1.0.0.dist-info/WHEEL
paginate_pandas-1.0.0.dist-info/top_level.txt
paginate_pandas-1.0.0.dist-info/RECORD
