Metadata-Version: 2.1
Name: paginate-pandas
Version: 1.0.0
Summary: An interactive paginator for pandas Series and DataFrames in Jupyter.
Home-page: https://github.com/jmberros/paginate_pandas
Author: Juan Manuel Berros
Author-email: juanmaberros@gmail.com
License: MIT
Keywords: pandas,pagination,interactive,ipywidgets,jupyter
License-File: LICENSE
